paraproc.py
paraproc-0.1.3.dist-info/METADATA
paraproc-0.1.3.dist-info/RECORD
paraproc-0.1.3.dist-info/WHEEL
paraproc-0.1.3.dist-info/top_level.txt
