Metadata-Version: 2.1
Name: paraproc
Version: 0.1.3
Summary: Easy parallel processing in Python
Home-page: https://github.com/herrlich10/paraproc
Author: herrlich10
Author-email: herrlich10@gmail.com
License: UNKNOWN
Platform: UNKNOWN
Classifier: Programming Language :: Python :: 2
Classifier: Programming Language :: Python :: 3
Classifier: Operating System :: OS Independent
Classifier: License :: OSI Approved :: MIT License
Classifier: Intended Audience :: Developers
Classifier: Intended Audience :: Science/Research
Classifier: Topic :: Software Development :: Libraries
Classifier: Topic :: Utilities
